pyshs/__init__.py
pyshs/_core.py
pyshs-0.3.8.dist-info/LICENSE
pyshs-0.3.8.dist-info/WHEEL
pyshs-0.3.8.dist-info/METADATA
pyshs-0.3.8.dist-info/RECORD
