Metadata-Version: 2.1
Name: pyshs
Version: 0.3.8
Summary: PySHS - Faciliter le traitement de données de questionnaires en SHS
Home-page: https://github.com/emilienschultz/pyshs-bib
Author: Emilien Schultz
Author-email: emilien.schultz@gmail.com
Requires-Python: >=3.7
Classifier: License :: OSI Approved :: MIT License
Requires-Dist: pandas
Requires-Dist: numpy
Requires-Dist: statsmodels
Requires-Dist: scipy
Requires-Dist: plotly
Requires-Dist: regex
Requires-Dist: openpyxl
Requires-Dist: samplics
Requires-Dist: matplotlib
Requires-Dist: seaborn
Requires-Dist: adjustText
